[{"arguments":["clang","-Wno-documentation-unknown-command","-Wno-unknown-warning-option","-Wno-unknown-pragmas","-nostdinc","-nostdinc++","-g","-std=gnu++1z","-Wall","-Wextra","-Wextra","-fexceptions","-mthreads","-fsyntax-only","-m64","--target=x86_64-w64-mingw32","-DUNICODE","-D_UNICODE","-DWIN32","-DMINGW_HAS_SECURE_API","-DQT_QML_DEBUG","-DQT_MULTIMEDIAWIDGETS_LIB","-DQT_WIDGETS_LIB","-DQT_MULTIMEDIA_LIB","-DQT_GUI_LIB","-DQT_NETWORK_LIB","-DQT_SQL_LIB","-DQT_CORE_LIB","-DQT_NEEDS_QMAIN","-DQ_CREATOR_RUN","-DQT_ANNOTATE_FUNCTION(x)=__attribute__((annotate(#x)))","-ID:\\C++\\Qt\\Tools\\QtCreator\\share\\qtcreator\\cplusplus\\wrappedMingwHeaders","-ID:\\C++\\Qt\\Tools\\QtCreator\\share\\qtcreator\\cplusplus\\wrappedQtHeaders","-ID:\\C++\\Qt\\Tools\\QtCreator\\share\\qtcreator\\cplusplus\\wrappedQtHeaders\\QtCore","-ID:\\C++\\QtOnline\\TetrisGames","-ID:\\C++\\Qt\\6.8.3\\mingw_64\\include","-ID:\\C++\\Qt\\6.8.3\\mingw_64\\include\\QtMultimediaWidgets","-ID:\\C++\\Qt\\6.8.3\\mingw_64\\include\\QtWidgets","-ID:\\C++\\Qt\\6.8.3\\mingw_64\\include\\QtMultimedia","-ID:\\C++\\Qt\\6.8.3\\mingw_64\\include\\QtGui","-ID:\\C++\\Qt\\6.8.3\\mingw_64\\include\\QtNetwork","-ID:\\C++\\Qt\\6.8.3\\mingw_64\\include\\QtSql","-ID:\\C++\\Qt\\6.8.3\\mingw_64\\include\\QtCore","-ID:\\C++\\QtOnline\\TetrisGames\\build\\Desktop_Qt_6_8_3_MinGW_64_bit-Debug\\debug","-ID:\\C++\\QtOnline\\TetrisGames\\build\\Desktop_Qt_6_8_3_MinGW_64_bit-Debug","-ID:\\C++\\Qt\\6.8.3\\mingw_64\\mkspecs\\win32-g++","-isystem","D:\\C++\\Qt\\Tools\\mingw1310_64\\lib\\gcc\\x86_64-w64-mingw32\\13.1.0\\include\\c++","-isystem","D:\\C++\\Qt\\Tools\\mingw1310_64\\lib\\gcc\\x86_64-w64-mingw32\\13.1.0\\include\\c++\\x86_64-w64-mingw32","-isystem","D:\\C++\\Qt\\Tools\\mingw1310_64\\lib\\gcc\\x86_64-w64-mingw32\\13.1.0\\include\\c++\\backward","-isystem","D:\\C++\\Qt\\Tools\\QtCreator\\bin\\clang\\lib\\clang\\21\\include","-isystem","D:\\C++\\Qt\\Tools\\mingw1310_64\\x86_64-w64-mingw32\\include","-fmessage-length=0","-fdiagnostics-show-note-include-stack","-fretain-comments-from-system-headers","-fmacro-backtrace-limit=0","-ferror-limit=1000","-x","c++","D:/C++/QtOnline/TetrisGames/lobby.cpp"],"directory":"D:/C++/QtOnline/TetrisGames/build/Desktop_Qt_6_8_3_MinGW_64_bit-Debug/.qtc_clangd","file":"D:/C++/QtOnline/TetrisGames/lobby.cpp"},{"arguments":["clang","-Wno-documentation-unknown-command","-Wno-unknown-warning-option","-Wno-unknown-pragmas","-nostdinc","-nostdinc++","-g","-std=gnu++1z","-Wall","-Wextra","-Wextra","-fexceptions","-mthreads","-fsyntax-only","-m64","--target=x86_64-w64-mingw32","-DUNICODE","-D_UNICODE","-DWIN32","-DMINGW_HAS_SECURE_API","-DQT_QML_DEBUG","-DQT_MULTIMEDIAWIDGETS_LIB","-DQT_WIDGETS_LIB","-DQT_MULTIMEDIA_LIB","-DQT_GUI_LIB","-DQT_NETWORK_LIB","-DQT_SQL_LIB","-DQT_CORE_LIB","-DQT_NEEDS_QMAIN","-DQ_CREATOR_RUN","-DQT_ANNOTATE_FUNCTION(x)=__attribute__((annotate(#x)))","-ID:\\C++\\Qt\\Tools\\QtCreator\\share\\qtcreator\\cplusplus\\wrappedMingwHeaders","-ID:\\C++\\Qt\\Tools\\QtCreator\\share\\qtcreator\\cplusplus\\wrappedQtHeaders","-ID:\\C++\\Qt\\Tools\\QtCreator\\share\\qtcreator\\cplusplus\\wrappedQtHeaders\\QtCore","-ID:\\C++\\QtOnline\\TetrisGames","-ID:\\C++\\Qt\\6.8.3\\mingw_64\\include","-ID:\\C++\\Qt\\6.8.3\\mingw_64\\include\\QtMultimediaWidgets","-ID:\\C++\\Qt\\6.8.3\\mingw_64\\include\\QtWidgets","-ID:\\C++\\Qt\\6.8.3\\mingw_64\\include\\QtMultimedia","-ID:\\C++\\Qt\\6.8.3\\mingw_64\\include\\QtGui","-ID:\\C++\\Qt\\6.8.3\\mingw_64\\include\\QtNetwork","-ID:\\C++\\Qt\\6.8.3\\mingw_64\\include\\QtSql","-ID:\\C++\\Qt\\6.8.3\\mingw_64\\include\\QtCore","-ID:\\C++\\QtOnline\\TetrisGames\\build\\Desktop_Qt_6_8_3_MinGW_64_bit-Debug\\debug","-ID:\\C++\\QtOnline\\TetrisGames\\build\\Desktop_Qt_6_8_3_MinGW_64_bit-Debug","-ID:\\C++\\Qt\\6.8.3\\mingw_64\\mkspecs\\win32-g++","-isystem","D:\\C++\\Qt\\Tools\\mingw1310_64\\lib\\gcc\\x86_64-w64-mingw32\\13.1.0\\include\\c++","-isystem","D:\\C++\\Qt\\Tools\\mingw1310_64\\lib\\gcc\\x86_64-w64-mingw32\\13.1.0\\include\\c++\\x86_64-w64-mingw32","-isystem","D:\\C++\\Qt\\Tools\\mingw1310_64\\lib\\gcc\\x86_64-w64-mingw32\\13.1.0\\include\\c++\\backward","-isystem","D:\\C++\\Qt\\Tools\\QtCreator\\bin\\clang\\lib\\clang\\21\\include","-isystem","D:\\C++\\Qt\\Tools\\mingw1310_64\\x86_64-w64-mingw32\\include","-fmessage-length=0","-fdiagnostics-show-note-include-stack","-fretain-comments-from-system-headers","-fmacro-backtrace-limit=0","-ferror-limit=1000","-x","c++","D:/C++/QtOnline/TetrisGames/main.cpp"],"directory":"D:/C++/QtOnline/TetrisGames/build/Desktop_Qt_6_8_3_MinGW_64_bit-Debug/.qtc_clangd","file":"D:/C++/QtOnline/TetrisGames/main.cpp"},{"arguments":["clang","-Wno-documentation-unknown-command","-Wno-unknown-warning-option","-Wno-unknown-pragmas","-nostdinc","-nostdinc++","-g","-std=gnu++1z","-Wall","-Wextra","-Wextra","-fexceptions","-mthreads","-fsyntax-only","-m64","--target=x86_64-w64-mingw32","-DUNICODE","-D_UNICODE","-DWIN32","-DMINGW_HAS_SECURE_API","-DQT_QML_DEBUG","-DQT_MULTIMEDIAWIDGETS_LIB","-DQT_WIDGETS_LIB","-DQT_MULTIMEDIA_LIB","-DQT_GUI_LIB","-DQT_NETWORK_LIB","-DQT_SQL_LIB","-DQT_CORE_LIB","-DQT_NEEDS_QMAIN","-DQ_CREATOR_RUN","-DQT_ANNOTATE_FUNCTION(x)=__attribute__((annotate(#x)))","-ID:\\C++\\Qt\\Tools\\QtCreator\\share\\qtcreator\\cplusplus\\wrappedMingwHeaders","-ID:\\C++\\Qt\\Tools\\QtCreator\\share\\qtcreator\\cplusplus\\wrappedQtHeaders","-ID:\\C++\\Qt\\Tools\\QtCreator\\share\\qtcreator\\cplusplus\\wrappedQtHeaders\\QtCore","-ID:\\C++\\QtOnline\\TetrisGames","-ID:\\C++\\Qt\\6.8.3\\mingw_64\\include","-ID:\\C++\\Qt\\6.8.3\\mingw_64\\include\\QtMultimediaWidgets","-ID:\\C++\\Qt\\6.8.3\\mingw_64\\include\\QtWidgets","-ID:\\C++\\Qt\\6.8.3\\mingw_64\\include\\QtMultimedia","-ID:\\C++\\Qt\\6.8.3\\mingw_64\\include\\QtGui","-ID:\\C++\\Qt\\6.8.3\\mingw_64\\include\\QtNetwork","-ID:\\C++\\Qt\\6.8.3\\mingw_64\\include\\QtSql","-ID:\\C++\\Qt\\6.8.3\\mingw_64\\include\\QtCore","-ID:\\C++\\QtOnline\\TetrisGames\\build\\Desktop_Qt_6_8_3_MinGW_64_bit-Debug\\debug","-ID:\\C++\\QtOnline\\TetrisGames\\build\\Desktop_Qt_6_8_3_MinGW_64_bit-Debug","-ID:\\C++\\Qt\\6.8.3\\mingw_64\\mkspecs\\win32-g++","-isystem","D:\\C++\\Qt\\Tools\\mingw1310_64\\lib\\gcc\\x86_64-w64-mingw32\\13.1.0\\include\\c++","-isystem","D:\\C++\\Qt\\Tools\\mingw1310_64\\lib\\gcc\\x86_64-w64-mingw32\\13.1.0\\include\\c++\\x86_64-w64-mingw32","-isystem","D:\\C++\\Qt\\Tools\\mingw1310_64\\lib\\gcc\\x86_64-w64-mingw32\\13.1.0\\include\\c++\\backward","-isystem","D:\\C++\\Qt\\Tools\\QtCreator\\bin\\clang\\lib\\clang\\21\\include","-isystem","D:\\C++\\Qt\\Tools\\mingw1310_64\\x86_64-w64-mingw32\\include","-fmessage-length=0","-fdiagnostics-show-note-include-stack","-fretain-comments-from-system-headers","-fmacro-backtrace-limit=0","-ferror-limit=1000","-x","c++","D:/C++/QtOnline/TetrisGames/mainwidget.cpp"],"directory":"D:/C++/QtOnline/TetrisGames/build/Desktop_Qt_6_8_3_MinGW_64_bit-Debug/.qtc_clangd","file":"D:/C++/QtOnline/TetrisGames/mainwidget.cpp"},{"arguments":["clang","-Wno-documentation-unknown-command","-Wno-unknown-warning-option","-Wno-unknown-pragmas","-nostdinc","-nostdinc++","-g","-std=gnu++1z","-Wall","-Wextra","-Wextra","-fexceptions","-mthreads","-fsyntax-only","-m64","--target=x86_64-w64-mingw32","-DUNICODE","-D_UNICODE","-DWIN32","-DMINGW_HAS_SECURE_API","-DQT_QML_DEBUG","-DQT_MULTIMEDIAWIDGETS_LIB","-DQT_WIDGETS_LIB","-DQT_MULTIMEDIA_LIB","-DQT_GUI_LIB","-DQT_NETWORK_LIB","-DQT_SQL_LIB","-DQT_CORE_LIB","-DQT_NEEDS_QMAIN","-DQ_CREATOR_RUN","-DQT_ANNOTATE_FUNCTION(x)=__attribute__((annotate(#x)))","-ID:\\C++\\Qt\\Tools\\QtCreator\\share\\qtcreator\\cplusplus\\wrappedMingwHeaders","-ID:\\C++\\Qt\\Tools\\QtCreator\\share\\qtcreator\\cplusplus\\wrappedQtHeaders","-ID:\\C++\\Qt\\Tools\\QtCreator\\share\\qtcreator\\cplusplus\\wrappedQtHeaders\\QtCore","-ID:\\C++\\QtOnline\\TetrisGames","-ID:\\C++\\Qt\\6.8.3\\mingw_64\\include","-ID:\\C++\\Qt\\6.8.3\\mingw_64\\include\\QtMultimediaWidgets","-ID:\\C++\\Qt\\6.8.3\\mingw_64\\include\\QtWidgets","-ID:\\C++\\Qt\\6.8.3\\mingw_64\\include\\QtMultimedia","-ID:\\C++\\Qt\\6.8.3\\mingw_64\\include\\QtGui","-ID:\\C++\\Qt\\6.8.3\\mingw_64\\include\\QtNetwork","-ID:\\C++\\Qt\\6.8.3\\mingw_64\\include\\QtSql","-ID:\\C++\\Qt\\6.8.3\\mingw_64\\include\\QtCore","-ID:\\C++\\QtOnline\\TetrisGames\\build\\Desktop_Qt_6_8_3_MinGW_64_bit-Debug\\debug","-ID:\\C++\\QtOnline\\TetrisGames\\build\\Desktop_Qt_6_8_3_MinGW_64_bit-Debug","-ID:\\C++\\Qt\\6.8.3\\mingw_64\\mkspecs\\win32-g++","-isystem","D:\\C++\\Qt\\Tools\\mingw1310_64\\lib\\gcc\\x86_64-w64-mingw32\\13.1.0\\include\\c++","-isystem","D:\\C++\\Qt\\Tools\\mingw1310_64\\lib\\gcc\\x86_64-w64-mingw32\\13.1.0\\include\\c++\\x86_64-w64-mingw32","-isystem","D:\\C++\\Qt\\Tools\\mingw1310_64\\lib\\gcc\\x86_64-w64-mingw32\\13.1.0\\include\\c++\\backward","-isystem","D:\\C++\\Qt\\Tools\\QtCreator\\bin\\clang\\lib\\clang\\21\\include","-isystem","D:\\C++\\Qt\\Tools\\mingw1310_64\\x86_64-w64-mingw32\\include","-fmessage-length=0","-fdiagnostics-show-note-include-stack","-fretain-comments-from-system-headers","-fmacro-backtrace-limit=0","-ferror-limit=1000","-x","c++","D:/C++/QtOnline/TetrisGames/rankingdialog.cpp"],"directory":"D:/C++/QtOnline/TetrisGames/build/Desktop_Qt_6_8_3_MinGW_64_bit-Debug/.qtc_clangd","file":"D:/C++/QtOnline/TetrisGames/rankingdialog.cpp"}]